openapi_client/__init__.py
openapi_client/api_client.py
openapi_client/api_response.py
openapi_client/configuration.py
openapi_client/exceptions.py
openapi_client/py.typed
openapi_client/rest.py
openapi_client/api/__init__.py
openapi_client/api/allocation_api.py
openapi_client/api/casing_api.py
openapi_client/api/daily_production_api.py
openapi_client/api/deviation_survey_api.py
openapi_client/api/down_hole_equipment_api.py
openapi_client/api/esp_api.py
openapi_client/api/forecast_api.py
openapi_client/api/formation_api.py
openapi_client/api/gas_lift_valve_api.py
openapi_client/api/horizontal_frac_api.py
openapi_client/api/micro_string_api.py
openapi_client/api/network_api.py
openapi_client/api/network_compressor_api.py
openapi_client/api/network_compressor_constraint_api.py
openapi_client/api/network_joint_constraint_api.py
openapi_client/api/network_pipe_api.py
openapi_client/api/network_pipe_constraint_api.py
openapi_client/api/network_screw_compressor_curve_api.py
openapi_client/api/network_source_api.py
openapi_client/api/network_source_forecast_api.py
openapi_client/api/network_well_api.py
openapi_client/api/network_well_constraint_api.py
openapi_client/api/pcp_api.py
openapi_client/api/sucker_rod_pump_api.py
openapi_client/api/timeseries_configuration_api.py
openapi_client/api/timeseries_history_api.py
openapi_client/api/tubing_api.py
openapi_client/api/well_api.py
openapi_client/api/well_event_api.py
openapi_client/api/well_test_api.py
openapi_client/api/wellbore_api.py
openapi_client/models/__init__.py
openapi_client/models/allocation.py
openapi_client/models/allocation_input.py
openapi_client/models/casing.py
openapi_client/models/casing_input.py
openapi_client/models/compressor_curve.py
openapi_client/models/compressor_curve_input.py
openapi_client/models/daily_production.py
openapi_client/models/daily_production_input.py
openapi_client/models/deviation_survey.py
openapi_client/models/deviation_survey_input.py
openapi_client/models/down_hole_equipment.py
xecta_data_api_client-2.0.20250908.1.dist-info/METADATA
xecta_data_api_client-2.0.20250908.1.dist-info/WHEEL
xecta_data_api_client-2.0.20250908.1.dist-info/top_level.txt
xecta_data_api_client-2.0.20250908.1.dist-info/RECORD
